cad/__init__.py
cad/dxf.py
cad/data/dxf/footer.dxf
cad/data/dxf/header.dxf
cad/data/dxf/polyline.dxf
cad/data/dxf/seqend.dxf
endocal/__init__.py
endocal/calibration.py
endocal/utils.py
endocal/data/sample_001/calibration_001-010.xml
endocal/data/sample_001/frame_001.jpg
endocal/data/sample_001/frame_002.jpg
endocal/data/sample_001/frame_003.jpg
endocal/data/sample_001/frame_004.jpg
endocal/data/sample_001/frame_005.jpg
endocal/data/sample_001/frame_006.jpg
endocal/data/sample_001/frame_007.jpg
endocal/data/sample_001/frame_008.jpg
endocal/data/sample_001/frame_009.jpg
endocal/data/sample_001/frame_010.jpg
endocal/data/sample_001/frame_011.jpg
endocal/data/sample_002/calibration_001-011.yml
endocal/data/sample_002/frame_001.jpg
endocal/data/sample_002/frame_002.jpg
endocal/data/sample_002/frame_003.jpg
endocal/data/sample_002/frame_004.jpg
endocal/data/sample_002/frame_005.jpg
endocal/data/sample_002/frame_006.jpg
endocal/data/sample_002/frame_007.jpg
endocal/data/sample_002/frame_008.jpg
endocal/data/sample_002/frame_009.jpg
endocal/data/sample_002/frame_010.jpg
endocal/data/sample_002/frame_011.jpg
endocal-18.2.13.dist-info/DESCRIPTION.rst
endocal-18.2.13.dist-info/METADATA
endocal-18.2.13.dist-info/RECORD
endocal-18.2.13.dist-info/WHEEL
endocal-18.2.13.dist-info/entry_points.txt
endocal-18.2.13.dist-info/metadata.json
endocal-18.2.13.dist-info/top_level.txt
