Metadata-Version: 2.0
Name: endocal
Version: 18.2.13
Summary: A cross-platform, compact GUI application for the optical distortion calibration of fluid-immersed endoscopes.
Home-page: https://github.com/gift-surg/endocal
Author: Dzhoshkun Ismail Shakir
Author-email: d.shakir@ucl.ac.uk
License: BSD-3-Clause
Keywords: optical distortion calibration,endoscope,endoscopy,medical imaging,image processing,biomedical engineering,medical physics,image-guided interventions
Platform: UNKNOWN
Classifier: Development Status :: 3 - Alpha
Classifier: Intended Audience :: Science/Research
Classifier: Intended Audience :: Healthcare Industry
Classifier: Topic :: Scientific/Engineering :: Medical Science Apps.
Classifier: Topic :: Scientific/Engineering :: Image Recognition
Classifier: Topic :: Multimedia :: Graphics
Classifier: Topic :: Multimedia :: Video :: Capture
Classifier: License :: OSI Approved :: BSD License
Classifier: Programming Language :: Python
Classifier: Operating System :: POSIX :: Linux
Classifier: Operating System :: MacOS :: MacOS X
Classifier: Operating System :: Microsoft :: Windows
Requires-Dist: PyYAML
Requires-Dist: numpy
